odoo8_addon_mrp_project-8.0.1.2.1-nspkg.pth
odoo_addons/mrp_project/README.rst
odoo_addons/mrp_project/__init__.py
odoo_addons/mrp_project/__openerp__.py
odoo_addons/mrp_project/i18n/ar.po
odoo_addons/mrp_project/i18n/ca.po
odoo_addons/mrp_project/i18n/de.po
odoo_addons/mrp_project/i18n/el_GR.po
odoo_addons/mrp_project/i18n/en_US.po
odoo_addons/mrp_project/i18n/es.po
odoo_addons/mrp_project/i18n/es_CR.po
odoo_addons/mrp_project/i18n/es_MX.po
odoo_addons/mrp_project/i18n/es_VE.po
odoo_addons/mrp_project/i18n/fi.po
odoo_addons/mrp_project/i18n/fr.po
odoo_addons/mrp_project/i18n/gl.po
odoo_addons/mrp_project/i18n/hr.po
odoo_addons/mrp_project/i18n/hr_HR.po
odoo_addons/mrp_project/i18n/hu.po
odoo_addons/mrp_project/i18n/it.po
odoo_addons/mrp_project/i18n/ja.po
odoo_addons/mrp_project/i18n/lt.po
odoo_addons/mrp_project/i18n/lv.po
odoo_addons/mrp_project/i18n/mk.po
odoo_addons/mrp_project/i18n/mn.po
odoo_addons/mrp_project/i18n/mrp_project.pot
odoo_addons/mrp_project/i18n/nb.po
odoo_addons/mrp_project/i18n/nl.po
odoo_addons/mrp_project/i18n/pl.po
odoo_addons/mrp_project/i18n/pt.po
odoo_addons/mrp_project/i18n/pt_BR.po
odoo_addons/mrp_project/i18n/pt_PT.po
odoo_addons/mrp_project/i18n/ro.po
odoo_addons/mrp_project/i18n/sk_SK.po
odoo_addons/mrp_project/i18n/sl.po
odoo_addons/mrp_project/i18n/sv.po
odoo_addons/mrp_project/i18n/tr.po
odoo_addons/mrp_project/i18n/uk.po
odoo_addons/mrp_project/i18n/vi_VN.po
odoo_addons/mrp_project/i18n/zh_CN.po
odoo_addons/mrp_project/models/__init__.py
odoo_addons/mrp_project/models/account_analytic_line.py
odoo_addons/mrp_project/models/hr_analytic_timesheet.py
odoo_addons/mrp_project/models/mrp_production.py
odoo_addons/mrp_project/models/project_project.py
odoo_addons/mrp_project/models/project_task.py
odoo_addons/mrp_project/models/project_task_work.py
odoo_addons/mrp_project/static/description/icon.png
odoo_addons/mrp_project/static/description/icon.svg
odoo_addons/mrp_project/tests/__init__.py
odoo8_addon_mrp_project-8.0.1.2.1.dist-info/METADATA
odoo8_addon_mrp_project-8.0.1.2.1.dist-info/WHEEL
odoo8_addon_mrp_project-8.0.1.2.1.dist-info/namespace_packages.txt
odoo8_addon_mrp_project-8.0.1.2.1.dist-info/top_level.txt
odoo8_addon_mrp_project-8.0.1.2.1.dist-info/RECORD
